mcp_shouji/__init__.py
mcp_shouji/__main__.py
mcp_shouji/debug.py
mcp_shouji/i18n.py
mcp_shouji/py.typed
mcp_shouji/server.py
mcp_shouji/desktop_app/__init__.py
mcp_shouji/desktop_app/desktop_app.py
mcp_shouji/desktop_release/__init__.py
mcp_shouji/desktop_release/mcp-shouji-desktop-linux
mcp_shouji/desktop_release/mcp-shouji-desktop-macos-arm64
mcp_shouji/desktop_release/mcp-shouji-desktop-macos-intel
mcp_shouji/desktop_release/mcp-shouji-desktop.exe
mcp_shouji/utils/__init__.py
mcp_shouji/utils/env_utils.py
mcp_shouji/utils/error_handler.py
mcp_shouji/utils/feedback_utils.py
mcp_shouji/utils/memory_monitor.py
mcp_shouji/utils/resource_manager.py
mcp_shouji/web/__init__.py
mcp_shouji/web/main.py
mcp_shouji/web/constants/__init__.py
mcp_shouji/web/constants/message_codes.py
mcp_shouji/web/locales/en/translation.json
mcp_shouji/web/locales/zh-CN/translation.json
mcp_shouji/web/locales/zh-TW/translation.json
mcp_shouji/web/models/__init__.py
mcp_shouji/web/models/feedback_result.py
mcp_shouji/web/models/feedback_session.py
mcp_shouji/web/routes/__init__.py
mcp_shouji/web/routes/main_routes.py
mcp_shouji/web/static/favicon.ico
mcp_shouji/web/static/icon-192.png
mcp_shouji/web/static/icon.svg
mcp_shouji/web/static/index.html
mcp_shouji/web/static/css/audio-management.css
mcp_shouji/web/static/css/notification-settings.css
mcp_shouji/web/static/css/prompt-management.css
mcp_shouji/web/static/css/session-management.css
mcp_shouji/web/static/css/styles.css
mcp_shouji/web/static/js/app.js
mcp_shouji/web/static/js/i18n.js
mcp_shouji/web/static/js/modules/connection-monitor.js
mcp_shouji/web/static/js/modules/file-upload-manager.js
mcp_shouji/web/static/js/modules/image-handler.js
mcp_shouji/web/static/js/modules/logger.js
mcp_shouji/web/static/js/modules/session-manager.js
mcp_shouji/web/static/js/modules/settings-manager.js
mcp_shouji/web/static/js/modules/tab-manager.js
mcp_shouji/web/static/js/modules/textarea-height-manager.js
mcp_shouji-2.6.0.dist-info/METADATA
mcp_shouji-2.6.0.dist-info/WHEEL
mcp_shouji-2.6.0.dist-info/entry_points.txt
mcp_shouji-2.6.0.dist-info/licenses/LICENSE
mcp_shouji-2.6.0.dist-info/RECORD
